marketpsych/__init__.py
marketpsych/mpwidgets.py
marketpsych/sftp.py
marketpsych-0.0.15.dist-info/LICENSE
marketpsych-0.0.15.dist-info/METADATA
marketpsych-0.0.15.dist-info/WHEEL
marketpsych-0.0.15.dist-info/top_level.txt
marketpsych-0.0.15.dist-info/RECORD
