Metadata-Version: 2.1
Name: marketpsych
Version: 0.0.15
Summary: Python libraries for working with MarketPsych's feeds
Home-page: https://github.com/marketpsych/marketpsych
Author: MarketPsych Data
License: MIT
Keywords: sentiment
Platform: UNKNOWN
Classifier: Development Status :: 3 - Alpha
Classifier: Intended Audience :: Developers
Classifier: License :: OSI Approved :: MIT License
Classifier: Programming Language :: Python :: 3
Requires-Python: >=3.6
License-File: LICENSE
Requires-Dist: dataclasses
Requires-Dist: datetime
Requires-Dist: ipywidgets
Requires-Dist: matplotlib
Requires-Dist: pandas
Requires-Dist: paramiko
